odoo/addons/kpi/README.rst
odoo/addons/kpi/__init__.py
odoo/addons/kpi/__manifest__.py
odoo/addons/kpi/data/kpi_data.xml
odoo/addons/kpi/i18n/am.po
odoo/addons/kpi/i18n/ar.po
odoo/addons/kpi/i18n/bg.po
odoo/addons/kpi/i18n/bs.po
odoo/addons/kpi/i18n/ca.po
odoo/addons/kpi/i18n/ca_ES.po
odoo/addons/kpi/i18n/cs.po
odoo/addons/kpi/i18n/da.po
odoo/addons/kpi/i18n/de.po
odoo/addons/kpi/i18n/el_GR.po
odoo/addons/kpi/i18n/en_GB.po
odoo/addons/kpi/i18n/es.po
odoo/addons/kpi/i18n/es_AR.po
odoo/addons/kpi/i18n/es_CL.po
odoo/addons/kpi/i18n/es_CO.po
odoo/addons/kpi/i18n/es_CR.po
odoo/addons/kpi/i18n/es_DO.po
odoo/addons/kpi/i18n/es_EC.po
odoo/addons/kpi/i18n/es_ES.po
odoo/addons/kpi/i18n/es_MX.po
odoo/addons/kpi/i18n/es_PE.po
odoo/addons/kpi/i18n/es_PY.po
odoo/addons/kpi/i18n/es_VE.po
odoo/addons/kpi/i18n/et.po
odoo/addons/kpi/i18n/eu.po
odoo/addons/kpi/i18n/fa.po
odoo/addons/kpi/i18n/fi.po
odoo/addons/kpi/i18n/fr.po
odoo/addons/kpi/i18n/fr_CA.po
odoo/addons/kpi/i18n/fr_CH.po
odoo/addons/kpi/i18n/fr_FR.po
odoo/addons/kpi/i18n/gl.po
odoo/addons/kpi/i18n/gl_ES.po
odoo/addons/kpi/i18n/he.po
odoo/addons/kpi/i18n/hr.po
odoo/addons/kpi/i18n/hr_HR.po
odoo/addons/kpi/i18n/hu.po
odoo/addons/kpi/i18n/id.po
odoo/addons/kpi/i18n/it.po
odoo/addons/kpi/i18n/ja.po
odoo/addons/kpi/i18n/ko.po
odoo/addons/kpi/i18n/kpi.pot
odoo/addons/kpi/i18n/lt.po
odoo/addons/kpi/i18n/lt_LT.po
odoo/addons/kpi/i18n/lv.po
odoo/addons/kpi/i18n/mk.po
odoo/addons/kpi/i18n/mn.po
odoo/addons/kpi/i18n/nb.po
odoo/addons/kpi/i18n/nb_NO.po
odoo/addons/kpi/i18n/nl.po
odoo/addons/kpi/i18n/nl_BE.po
odoo/addons/kpi/i18n/nl_NL.po
odoo/addons/kpi/i18n/pl.po
odoo/addons/kpi/i18n/pt.po
odoo/addons/kpi/i18n/pt_BR.po
odoo/addons/kpi/i18n/pt_PT.po
odoo/addons/kpi/i18n/ro.po
odoo/addons/kpi/i18n/ru.po
odoo/addons/kpi/i18n/sk.po
odoo/addons/kpi/i18n/sl.po
odoo/addons/kpi/i18n/sr.po
odoo/addons/kpi/i18n/sr@latin.po
odoo/addons/kpi/i18n/sv.po
odoo/addons/kpi/i18n/th.po
odoo/addons/kpi/i18n/tr.po
odoo/addons/kpi/i18n/tr_TR.po
odoo12_addon_kpi-12.0.1.0.1.dist-info/METADATA
odoo12_addon_kpi-12.0.1.0.1.dist-info/WHEEL
odoo12_addon_kpi-12.0.1.0.1.dist-info/top_level.txt
odoo12_addon_kpi-12.0.1.0.1.dist-info/RECORD
